[
  {
    "name" : "温玉豚キムチ丼",
    "img" : "https:\/\/west2-univ.jp\/menu_img\/png_sp\/819058.png",
    "price" : "中440"
  },
  {
    "name" : "温玉豚キムチ丼",
    "price" : "小385",
    "img" : "https:\/\/west2-univ.jp\/menu_img\/png_sp\/819058.png"
  },
  {
    "price" : "大495",
    "img" : "https:\/\/west2-univ.jp\/menu_img\/png_sp\/819058.png",
    "name" : "温玉豚キムチ丼"
  },
  {
    "name" : "味噌カツ丼",
    "price" : "中440",
    "img" : "https:\/\/west2-univ.jp\/menu_img\/png_sp\/819073.png"
  },
  {
    "name" : "味噌カツ丼",
    "price" : "小385",
    "img" : "https:\/\/west2-univ.jp\/menu_img\/png_sp\/819073.png"
  },
  {
    "price" : "大495",
    "img" : "https:\/\/west2-univ.jp\/menu_img\/png_sp\/819073.png",
    "name" : "味噌カツ丼"
  },
  {
    "name" : "ロースカツカレー",
    "price" : "中440",
    "img" : "https:\/\/west2-univ.jp\/menu_img\/png_sp\/819253.png"
  },
  {
    "img" : "https:\/\/west2-univ.jp\/menu_img\/png_sp\/819253.png",
    "price" : "小385",
    "name" : "ロースカツカレー"
  },
  {
    "name" : "ロースカツカレー",
    "price" : "大495",
    "img" : "https:\/\/west2-univ.jp\/menu_img\/png_sp\/819253.png"
  },
  {
    "price" : "中319",
    "name" : "カレーライス",
    "img" : "https:\/\/west2-univ.jp\/menu_img\/png_sp\/819272.png"
  },
  {
    "name" : "カレーライス",
    "img" : "https:\/\/west2-univ.jp\/menu_img\/png_sp\/819272.png",
    "price" : "小264"
  },
  {
    "img" : "https:\/\/west2-univ.jp\/menu_img\/png_sp\/819272.png",
    "price" : "大374",
    "name" : "カレーライス"
  },
  {
    "price" : "中126",
    "name" : "ライス",
    "img" : "https:\/\/west2-univ.jp\/menu_img\/png_sp\/814702.png"
  },
  {
    "img" : "https:\/\/west2-univ.jp\/menu_img\/png_sp\/814702.png",
    "name" : "ライス",
    "price" : "小105"
  },
  {
    "price" : "大147",
    "name" : "ライス",
    "img" : "https:\/\/west2-univ.jp\/menu_img\/png_sp\/814702.png"
  }
]