{
  "cafes" : [
    {
      "foods" : [
        {
          "name" : "ジューシー鶏カツオーロラソース",
          "price" : "374",
          "attr" : "a",
          "img" : "https:\/\/west2-univ.jp\/menu_img\/png_sp\/814283.png"
        },
        {
          "img" : "https:\/\/west2-univ.jp\/menu_img\/png_sp\/814024.png",
          "price" : "330",
          "attr" : "a",
          "name" : "ローストンカツデミソース"
        },
        {
          "price" : "242",
          "attr" : "a",
          "img" : "https:\/\/west2-univ.jp\/menu_img\/png_sp\/814163.png",
          "name" : "いわし梅しそフライ"
        },
        {
          "name" : "照りタルハンバーグ",
          "price" : "286",
          "attr" : "a",
          "img" : "https:\/\/west2-univ.jp\/menu_img\/png_sp\/814055.png"
        },
        {
          "attr" : "a",
          "price" : "286",
          "name" : "ダッカルビ風野菜炒め",
          "img" : "https:\/\/west2-univ.jp\/menu_img\/png_sp\/814257.png"
        },
        {
          "img" : "https:\/\/west2-univ.jp\/menu_img\/png_sp\/814021.png",
          "attr" : "a",
          "name" : "鶏醤油ちゃんこ煮",
          "price" : "286"
        },
        {
          "img" : "https:\/\/west2-univ.jp\/menu_img\/png_sp\/814297.png",
          "attr" : "a",
          "name" : "鯖味噌煮",
          "price" : "242"
        }
      ],
      "name" : "Rune"
    },
    {
      "name" : "Rune",
      "foods" : [
        {
          "name" : "南瓜コロッケ",
          "price" : "121",
          "img" : "https:\/\/west2-univ.jp\/menu_img\/png_sp\/814409.png",
          "attr" : "b"
        },
        {
          "price" : "77",
          "attr" : "b",
          "name" : "塩蒸し南瓜 ",
          "img" : "https:\/\/west2-univ.jp\/menu_img\/png_sp\/650118_449496.png"
        },
        {
          "price" : "99",
          "img" : "https:\/\/west2-univ.jp\/menu_img\/png_sp\/814448.png",
          "attr" : "b",
          "name" : "巣ごもり玉子"
        },
        {
          "img" : "https:\/\/west2-univ.jp\/menu_img\/png_sp\/814539.png",
          "name" : "竹の子土佐煮",
          "price" : "99",
          "attr" : "b"
        },
        {
          "attr" : "b",
          "name" : "春雨しそサラダ",
          "price" : "99",
          "img" : "https:\/\/west2-univ.jp\/menu_img\/png_sp\/814477.png"
        },
        {
          "name" : "きんぴらごぼう",
          "price" : "77",
          "attr" : "b",
          "img" : "https:\/\/west2-univ.jp\/menu_img\/png_sp\/814552.png"
        },
        {
          "price" : "99",
          "attr" : "b",
          "img" : "https:\/\/west2-univ.jp\/menu_img\/png_sp\/814554.png",
          "name" : "茄子のピリ辛胡麻風味"
        },
        {
          "price" : "77",
          "name" : "だし巻き",
          "attr" : "b",
          "img" : "https:\/\/west2-univ.jp\/menu_img\/png_sp\/814453.png"
        },
        {
          "attr" : "b",
          "name" : "きんぴらごぼう",
          "price" : "77",
          "img" : "https:\/\/west2-univ.jp\/menu_img\/png_sp\/814552.png"
        },
        {
          "img" : "https:\/\/west2-univ.jp\/menu_img\/png_sp\/814454.png",
          "price" : "77",
          "attr" : "b",
          "name" : "スライスオクラ"
        },
        {
          "attr" : "b",
          "img" : "https:\/\/west2-univ.jp\/menu_img\/png_sp\/814455.png",
          "name" : "冷奴",
          "price" : "55"
        },
        {
          "img" : "https:\/\/west2-univ.jp\/menu_img\/png_sp\/814667.png",
          "price" : "121",
          "name" : "豚汁",
          "attr" : "b"
        },
        {
          "name" : "味噌汁",
          "img" : "https:\/\/west2-univ.jp\/menu_img\/png_sp\/814666.png",
          "attr" : "b",
          "price" : "44"
        }
      ]
    },
    {
      "name" : "Rune",
      "foods" : [
        {
          "attr" : "d",
          "img" : "https:\/\/west2-univ.jp\/menu_img\/png_sp\/650118_446040.png",
          "price" : "中495",
          "name" : "サーモン炙りハラス丼"
        },
        {
          "price" : "中319",
          "name" : "カレーライス",
          "attr" : "d",
          "img" : "https:\/\/west2-univ.jp\/menu_img\/png_sp\/819272.png"
        },
        {
          "attr" : "d",
          "name" : "ライス",
          "price" : "中126",
          "img" : "https:\/\/west2-univ.jp\/menu_img\/png_sp\/814702.png"
        },
        {
          "img" : "https:\/\/west2-univ.jp\/menu_img\/png_sp\/814702.png",
          "attr" : "d",
          "name" : "ライス",
          "price" : "小105"
        },
        {
          "price" : "大147",
          "attr" : "d",
          "img" : "https:\/\/west2-univ.jp\/menu_img\/png_sp\/814702.png",
          "name" : "ライス"
        }
      ]
    },
    {
      "name" : "Rune",
      "foods" : [
        {
          "img" : "https:\/\/west2-univ.jp\/menu_img\/png_sp\/814841.png",
          "attr" : "e",
          "price" : "176",
          "name" : "ミルクティーショート"
        },
        {
          "name" : "フルーツヨーグルト",
          "price" : "132",
          "img" : "https:\/\/west2-univ.jp\/menu_img\/png_sp\/814808.png",
          "attr" : "e"
        },
        {
          "attr" : "e",
          "name" : "バナナクレープ",
          "price" : "88",
          "img" : "https:\/\/west2-univ.jp\/menu_img\/png_sp\/814890.png"
        },
        {
          "img" : "https:\/\/west2-univ.jp\/menu_img\/png_sp\/814817.png",
          "name" : "大学芋",
          "price" : "110",
          "attr" : "e"
        },
        {
          "img" : "https:\/\/west2-univ.jp\/menu_img\/png_sp\/814816.png",
          "name" : "牛乳",
          "price" : "98",
          "attr" : "e"
        },
        {
          "price" : "105",
          "img" : "https:\/\/west2-univ.jp\/menu_img\/png_sp\/814818.png",
          "name" : "大学生協コーヒー",
          "attr" : "e"
        }
      ]
    },
    {
      "foods" : [
        {
          "price" : "495",
          "attr" : "1",
          "img" : "https:\/\/west2-univ.jp\/menu_img\/png_sp\/650118_447378.png",
          "name" : "塩だれ天津飯"
        }
      ],
      "name" : "Rune"
    },
    {
      "name" : "Rune",
      "foods" : [
        {
          "img" : "https:\/\/west2-univ.jp\/menu_img\/png_sp\/650118_449047.png",
          "attr" : "2",
          "price" : "550",
          "name" : "ケバブプレート"
        },
        {
          "price" : "495",
          "img" : "https:\/\/west2-univ.jp\/menu_img\/png_sp\/650118_449046.png",
          "attr" : "2",
          "name" : "ケバブラップ"
        },
        {
          "name" : "ベジラップ",
          "img" : "https:\/\/west2-univ.jp\/menu_img\/png_sp\/650118_449202.png",
          "attr" : "2",
          "price" : "495"
        },
        {
          "img" : "https:\/\/west2-univ.jp\/menu_img\/png_sp\/650118_449208.png",
          "attr" : "2",
          "name" : "3種豆のベジカレープレート",
          "price" : "550"
        }
      ]
    },
    {
      "name" : "Rune",
      "foods" : [
        {
          "price" : "330",
          "img" : "https:\/\/west2-univ.jp\/menu_img\/png_sp\/650118_449000.png",
          "attr" : "3",
          "name" : "コーヒーゼリーパフェ"
        },
        {
          "attr" : "3",
          "price" : "330",
          "img" : "https:\/\/west2-univ.jp\/menu_img\/png_sp\/650118_449002.png",
          "name" : "ヨーグルトパフェ"
        },
        {
          "img" : "https:\/\/west2-univ.jp\/menu_img\/png_sp\/650118_449006.png",
          "price" : "385",
          "name" : "プリンパフェ",
          "attr" : "3"
        },
        {
          "price" : "440",
          "name" : "＊カッサータ風パフェ",
          "attr" : "3",
          "img" : "https:\/\/west2-univ.jp\/menu_img\/png_sp\/650118_449400.png"
        },
        {
          "name" : "＊イギリス風紅茶香るアップルパフェ",
          "price" : "0",
          "attr" : "3",
          "img" : "https:\/\/west2-univ.jp\/menu_img\/png_sp\/650118_449303.png"
        },
        {
          "img" : "https:\/\/west2-univ.jp\/menu_img\/png_sp\/650118_449010.png",
          "name" : "ルネBIGパフェ",
          "price" : "550",
          "attr" : "3"
        }
      ]
    },
    {
      "name" : "Yoshida",
      "foods" : [
        {
          "price" : "374",
          "img" : "https:\/\/west2-univ.jp\/menu_img\/png_sp\/814128.png",
          "attr" : "a",
          "name" : "チキン南蛮"
        },
        {
          "img" : "https:\/\/west2-univ.jp\/menu_img\/png_sp\/814055.png",
          "attr" : "a",
          "price" : "286",
          "name" : "照りタルハンバーグ"
        },
        {
          "attr" : "a",
          "img" : "https:\/\/west2-univ.jp\/menu_img\/png_sp\/814021.png",
          "name" : "鶏醤油ちゃんこ煮",
          "price" : "286"
        },
        {
          "attr" : "a",
          "name" : "海老よせフライ",
          "price" : "242",
          "img" : "https:\/\/west2-univ.jp\/menu_img\/png_sp\/814309.png"
        },
        {
          "name" : "ブリの甘酢あん",
          "price" : "242",
          "img" : "https:\/\/west2-univ.jp\/menu_img\/png_sp\/814314.png",
          "attr" : "a"
        }
      ]
    },
    {
      "name" : "Yoshida",
      "foods" : [
        {
          "img" : "https:\/\/west2-univ.jp\/menu_img\/png_sp\/814418.png",
          "price" : "121",
          "attr" : "b",
          "name" : "ポテト野菜サラダ"
        },
        {
          "price" : "121",
          "img" : "https:\/\/west2-univ.jp\/menu_img\/png_sp\/814409.png",
          "attr" : "b",
          "name" : "南瓜コロッケ"
        },
        {
          "attr" : "b",
          "name" : "オクラ巣ごもり玉子",
          "price" : "99",
          "img" : "https:\/\/west2-univ.jp\/menu_img\/png_sp\/814447.png"
        },
        {
          "img" : "https:\/\/west2-univ.jp\/menu_img\/png_sp\/814554.png",
          "name" : "茄子のピリ辛胡麻風味",
          "price" : "99",
          "attr" : "b"
        },
        {
          "img" : "https:\/\/west2-univ.jp\/menu_img\/png_sp\/814477.png",
          "name" : "春雨しそサラダ",
          "attr" : "b",
          "price" : "99"
        },
        {
          "price" : "99",
          "name" : "ほうれん草ごまナムル",
          "img" : "https:\/\/west2-univ.jp\/menu_img\/png_sp\/814578.png",
          "attr" : "b"
        },
        {
          "img" : "https:\/\/west2-univ.jp\/menu_img\/png_sp\/814433.png",
          "attr" : "b",
          "name" : "ほうれん草胡麻和え",
          "price" : "77"
        },
        {
          "attr" : "b",
          "name" : "納豆",
          "price" : "55",
          "img" : "https:\/\/west2-univ.jp\/menu_img\/png_sp\/814457.png"
        },
        {
          "name" : "冷奴",
          "price" : "55",
          "attr" : "b",
          "img" : "https:\/\/west2-univ.jp\/menu_img\/png_sp\/814455.png"
        },
        {
          "price" : "55",
          "attr" : "b",
          "name" : "ミニサラダ",
          "img" : "https:\/\/west2-univ.jp\/menu_img\/png_sp\/814460.png"
        },
        {
          "name" : "豚汁",
          "attr" : "b",
          "price" : "121",
          "img" : "https:\/\/west2-univ.jp\/menu_img\/png_sp\/814667.png"
        },
        {
          "img" : "https:\/\/west2-univ.jp\/menu_img\/png_sp\/814666.png",
          "price" : "44",
          "attr" : "b",
          "name" : "味噌汁"
        }
      ]
    },
    {
      "name" : "Yoshida",
      "foods" : [
        {
          "attr" : "d",
          "name" : "サーモン炙りハラス丼",
          "img" : "https:\/\/west2-univ.jp\/menu_img\/png_sp\/650118_446040.png",
          "price" : "中495"
        },
        {
          "price" : "中440",
          "img" : "https:\/\/west2-univ.jp\/menu_img\/png_sp\/819256.png",
          "attr" : "d",
          "name" : "唐揚げカレー"
        },
        {
          "price" : "小385",
          "img" : "https:\/\/west2-univ.jp\/menu_img\/png_sp\/819256.png",
          "name" : "唐揚げカレー",
          "attr" : "d"
        },
        {
          "img" : "https:\/\/west2-univ.jp\/menu_img\/png_sp\/819256.png",
          "attr" : "d",
          "price" : "大495",
          "name" : "唐揚げカレー"
        },
        {
          "name" : "カレーライス",
          "price" : "中319",
          "attr" : "d",
          "img" : "https:\/\/west2-univ.jp\/menu_img\/png_sp\/819272.png"
        },
        {
          "price" : "小264",
          "name" : "カレーライス",
          "attr" : "d",
          "img" : "https:\/\/west2-univ.jp\/menu_img\/png_sp\/819272.png"
        },
        {
          "attr" : "d",
          "img" : "https:\/\/west2-univ.jp\/menu_img\/png_sp\/819272.png",
          "price" : "大374",
          "name" : "カレーライス"
        },
        {
          "attr" : "d",
          "img" : "https:\/\/west2-univ.jp\/menu_img\/png_sp\/814702.png",
          "price" : "中126",
          "name" : "ライス"
        },
        {
          "attr" : "d",
          "img" : "https:\/\/west2-univ.jp\/menu_img\/png_sp\/814702.png",
          "price" : "小105",
          "name" : "ライス"
        },
        {
          "name" : "ライス",
          "price" : "大147",
          "attr" : "d",
          "img" : "https:\/\/west2-univ.jp\/menu_img\/png_sp\/814702.png"
        }
      ]
    },
    {
      "name" : "Yoshida",
      "foods" : [
        {
          "name" : "ミルクティーショート",
          "img" : "https:\/\/west2-univ.jp\/menu_img\/png_sp\/814841.png",
          "attr" : "e",
          "price" : "176"
        },
        {
          "name" : "フルーツヨーグルト",
          "attr" : "e",
          "price" : "132",
          "img" : "https:\/\/west2-univ.jp\/menu_img\/png_sp\/814808.png"
        },
        {
          "price" : "88",
          "img" : "https:\/\/west2-univ.jp\/menu_img\/png_sp\/814890.png",
          "attr" : "e",
          "name" : "バナナクレープ"
        },
        {
          "name" : "大学芋",
          "price" : "110",
          "attr" : "e",
          "img" : "https:\/\/west2-univ.jp\/menu_img\/png_sp\/814817.png"
        },
        {
          "price" : "98",
          "img" : "https:\/\/west2-univ.jp\/menu_img\/png_sp\/814816.png",
          "attr" : "e",
          "name" : "牛乳"
        },
        {
          "attr" : "e",
          "img" : "https:\/\/west2-univ.jp\/menu_img\/png_sp\/814818.png",
          "name" : "大学生協コーヒー",
          "price" : "105"
        }
      ]
    },
    {
      "foods" : [
        {
          "price" : "286",
          "attr" : "a",
          "img" : "https:\/\/west2-univ.jp\/menu_img\/png_sp\/814055.png",
          "name" : "照りタルハンバーグ"
        },
        {
          "name" : "ローストンカツおろしソース",
          "attr" : "a",
          "price" : "330",
          "img" : "https:\/\/west2-univ.jp\/menu_img\/png_sp\/814022.png"
        },
        {
          "img" : "https:\/\/west2-univ.jp\/menu_img\/png_sp\/814174.png",
          "name" : "フライドチキン",
          "attr" : "a",
          "price" : "198"
        },
        {
          "img" : "https:\/\/west2-univ.jp\/menu_img\/png_sp\/814067.png",
          "price" : "286",
          "name" : "豆腐とあさりのうま塩煮",
          "attr" : "a"
        },
        {
          "price" : "242",
          "img" : "https:\/\/west2-univ.jp\/menu_img\/png_sp\/814297.png",
          "name" : "鯖味噌煮",
          "attr" : "a"
        },
        {
          "img" : "https:\/\/west2-univ.jp\/menu_img\/png_sp\/814298.png",
          "price" : "242",
          "attr" : "a",
          "name" : "鯖生姜煮"
        }
      ],
      "name" : "Kinki"
    },
    {
      "foods" : [
        {
          "name" : "オクラ巣ごもり玉子",
          "attr" : "b",
          "price" : "99",
          "img" : "https:\/\/west2-univ.jp\/menu_img\/png_sp\/814447.png"
        },
        {
          "name" : "だし巻き",
          "price" : "77",
          "img" : "https:\/\/west2-univ.jp\/menu_img\/png_sp\/814453.png",
          "attr" : "b"
        },
        {
          "attr" : "b",
          "price" : "55",
          "name" : "冷奴",
          "img" : "https:\/\/west2-univ.jp\/menu_img\/png_sp\/814455.png"
        },
        {
          "price" : "99",
          "name" : "スタミナ茄子",
          "attr" : "b",
          "img" : "https:\/\/west2-univ.jp\/menu_img\/png_sp\/814536.png"
        },
        {
          "price" : "99",
          "img" : "https:\/\/west2-univ.jp\/menu_img\/png_sp\/814579.png",
          "name" : "小松菜わさび和え",
          "attr" : "b"
        },
        {
          "price" : "77",
          "attr" : "b",
          "img" : "https:\/\/west2-univ.jp\/menu_img\/png_sp\/814551.png",
          "name" : "ポテトサラダ"
        },
        {
          "price" : "77",
          "img" : "https:\/\/west2-univ.jp\/menu_img\/png_sp\/814433.png",
          "name" : "ほうれん草胡麻和え",
          "attr" : "b"
        },
        {
          "name" : "ブロッコリーピーナッツ和え",
          "img" : "https:\/\/west2-univ.jp\/menu_img\/png_sp\/814413.png",
          "price" : "99",
          "attr" : "b"
        },
        {
          "price" : "99",
          "attr" : "b",
          "name" : "小松菜わさび和え",
          "img" : "https:\/\/west2-univ.jp\/menu_img\/png_sp\/814579.png"
        },
        {
          "img" : "https:\/\/west2-univ.jp\/menu_img\/png_sp\/814412.png",
          "name" : "ねぎだくもやしナムル",
          "price" : "99",
          "attr" : "b"
        },
        {
          "img" : "https:\/\/west2-univ.jp\/menu_img\/png_sp\/814563.png",
          "price" : "99",
          "attr" : "b",
          "name" : "鶏とオクラの柚子胡椒和え"
        },
        {
          "name" : "ちくわの磯部揚げ",
          "price" : "121",
          "img" : "https:\/\/west2-univ.jp\/menu_img\/png_sp\/814465.png",
          "attr" : "b"
        },
        {
          "price" : "77",
          "name" : "肉団子",
          "img" : "https:\/\/west2-univ.jp\/menu_img\/png_sp\/814432.png",
          "attr" : "b"
        },
        {
          "name" : "豚汁",
          "price" : "121",
          "img" : "https:\/\/west2-univ.jp\/menu_img\/png_sp\/814667.png",
          "attr" : "b"
        },
        {
          "img" : "https:\/\/west2-univ.jp\/menu_img\/png_sp\/814666.png",
          "attr" : "b",
          "price" : "44",
          "name" : "味噌汁"
        },
        {
          "attr" : "b",
          "price" : "55",
          "name" : "納豆",
          "img" : "https:\/\/west2-univ.jp\/menu_img\/png_sp\/814457.png"
        }
      ],
      "name" : "Kinki"
    },
    {
      "foods" : [
        {
          "img" : "https:\/\/west2-univ.jp\/menu_img\/png_sp\/819393.png",
          "name" : "きつねうどん",
          "price" : "352",
          "attr" : "c"
        },
        {
          "img" : "https:\/\/west2-univ.jp\/menu_img\/png_sp\/819329.png",
          "price" : "264",
          "attr" : "c",
          "name" : "かけそば"
        },
        {
          "name" : "醤油豚骨ラーメン",
          "price" : "462",
          "img" : "https:\/\/west2-univ.jp\/menu_img\/png_sp\/819445.png",
          "attr" : "c"
        }
      ],
      "name" : "Kinki"
    },
    {
      "foods" : [
        {
          "attr" : "d",
          "name" : "和風カツ丼",
          "price" : "中440",
          "img" : "https:\/\/west2-univ.jp\/menu_img\/png_sp\/819085.png"
        },
        {
          "attr" : "d",
          "price" : "中440",
          "name" : "たっぷりチーズカレー",
          "img" : "https:\/\/west2-univ.jp\/menu_img\/png_sp\/819238.png"
        },
        {
          "attr" : "d",
          "price" : "中126",
          "name" : "ライス",
          "img" : "https:\/\/west2-univ.jp\/menu_img\/png_sp\/814702.png"
        }
      ],
      "name" : "Kinki"
    },
    {
      "foods" : [
        {
          "name" : "焼きプリンタルト",
          "attr" : "e",
          "price" : "88",
          "img" : "https:\/\/west2-univ.jp\/menu_img\/png_sp\/814813.png"
        },
        {
          "attr" : "e",
          "price" : "88",
          "name" : "イチゴシュー",
          "img" : "https:\/\/west2-univ.jp\/menu_img\/png_sp\/814875.png"
        },
        {
          "img" : "https:\/\/west2-univ.jp\/menu_img\/png_sp\/814890.png",
          "name" : "バナナクレープ",
          "attr" : "e",
          "price" : "88"
        },
        {
          "attr" : "e",
          "price" : "110",
          "name" : "大学芋",
          "img" : "https:\/\/west2-univ.jp\/menu_img\/png_sp\/814817.png"
        },
        {
          "attr" : "e",
          "price" : "98",
          "img" : "https:\/\/west2-univ.jp\/menu_img\/png_sp\/814816.png",
          "name" : "牛乳"
        },
        {
          "price" : "105",
          "img" : "https:\/\/west2-univ.jp\/menu_img\/png_sp\/814818.png",
          "attr" : "e",
          "name" : "大学生協コーヒー"
        }
      ],
      "name" : "Kinki"
    },
    {
      "foods" : [

      ],
      "name" : "Kinki"
    },
    {
      "name" : "Kinki",
      "foods" : [

      ]
    },
    {
      "name" : "Hokubu",
      "foods" : [
        {
          "price" : "374",
          "name" : "ジューシー鶏カツソースあんかけ",
          "attr" : "a",
          "img" : "https:\/\/west2-univ.jp\/menu_img\/png_sp\/814282.png"
        },
        {
          "name" : "ローストンカツ玉子あんかけ",
          "img" : "https:\/\/west2-univ.jp\/menu_img\/png_sp\/814311.png",
          "price" : "330",
          "attr" : "a"
        },
        {
          "name" : "鯖塩焼き",
          "price" : "242",
          "img" : "https:\/\/west2-univ.jp\/menu_img\/png_sp\/814308.png",
          "attr" : "a"
        },
        {
          "name" : "照りタルハンバーグ",
          "price" : "286",
          "img" : "https:\/\/west2-univ.jp\/menu_img\/png_sp\/814055.png",
          "attr" : "a"
        },
        {
          "price" : "286",
          "attr" : "a",
          "img" : "https:\/\/west2-univ.jp\/menu_img\/png_sp\/814256.png",
          "name" : "鶏のチリソース炒め"
        },
        {
          "img" : "https:\/\/west2-univ.jp\/menu_img\/png_sp\/814066.png",
          "attr" : "a",
          "price" : "286",
          "name" : "豚すき煮"
        },
        {
          "price" : "121",
          "attr" : "a",
          "name" : "ちくわの磯部揚げ",
          "img" : "https:\/\/west2-univ.jp\/menu_img\/png_sp\/814465.png"
        },
        {
          "price" : "242",
          "attr" : "a",
          "img" : "https:\/\/west2-univ.jp\/menu_img\/png_sp\/814314.png",
          "name" : "ブリの甘酢あん"
        }
      ]
    },
    {
      "foods" : [
        {
          "img" : "https:\/\/west2-univ.jp\/menu_img\/png_sp\/814583.png",
          "attr" : "b",
          "price" : "99",
          "name" : "ささみ枝豆ひじきサラダ"
        },
        {
          "img" : "https:\/\/west2-univ.jp\/menu_img\/png_sp\/814421.png",
          "attr" : "b",
          "price" : "121",
          "name" : "海老クリームコロッケ"
        },
        {
          "name" : "小松菜わさび和え",
          "price" : "99",
          "img" : "https:\/\/west2-univ.jp\/menu_img\/png_sp\/814579.png",
          "attr" : "b"
        },
        {
          "attr" : "b",
          "name" : "茄子のピリ辛胡麻風味",
          "img" : "https:\/\/west2-univ.jp\/menu_img\/png_sp\/814554.png",
          "price" : "99"
        },
        {
          "img" : "https:\/\/west2-univ.jp\/menu_img\/png_sp\/814454.png",
          "attr" : "b",
          "name" : "スライスオクラ",
          "price" : "77"
        },
        {
          "img" : "https:\/\/west2-univ.jp\/menu_img\/png_sp\/814477.png",
          "price" : "99",
          "attr" : "b",
          "name" : "春雨しそサラダ"
        },
        {
          "name" : "豆たっぷりヘルシーサラダ",
          "price" : "77",
          "attr" : "b",
          "img" : "https:\/\/west2-univ.jp\/menu_img\/png_sp\/814506.png"
        },
        {
          "attr" : "b",
          "name" : "千切り煮",
          "img" : "https:\/\/west2-univ.jp\/menu_img\/png_sp\/814577.png",
          "price" : "77"
        },
        {
          "img" : "https:\/\/west2-univ.jp\/menu_img\/png_sp\/814455.png",
          "price" : "55",
          "name" : "冷奴",
          "attr" : "b"
        },
        {
          "name" : "ミニサラダ",
          "price" : "55",
          "img" : "https:\/\/west2-univ.jp\/menu_img\/png_sp\/814460.png",
          "attr" : "b"
        },
        {
          "price" : "55",
          "img" : "https:\/\/west2-univ.jp\/menu_img\/png_sp\/814457.png",
          "attr" : "b",
          "name" : "納豆"
        },
        {
          "attr" : "b",
          "name" : "豚汁",
          "price" : "121",
          "img" : "https:\/\/west2-univ.jp\/menu_img\/png_sp\/814667.png"
        },
        {
          "attr" : "b",
          "img" : "https:\/\/west2-univ.jp\/menu_img\/png_sp\/814666.png",
          "price" : "44",
          "name" : "味噌汁"
        }
      ],
      "name" : "Hokubu"
    },
    {
      "name" : "Hokubu",
      "foods" : [
        {
          "price" : "中495",
          "img" : "https:\/\/west2-univ.jp\/menu_img\/png_sp\/650118_446040.png",
          "attr" : "d",
          "name" : "サーモン炙りハラス丼"
        },
        {
          "attr" : "d",
          "name" : "チキンカツカレー",
          "price" : "中440",
          "img" : "https:\/\/west2-univ.jp\/menu_img\/png_sp\/819259.png"
        },
        {
          "img" : "https:\/\/west2-univ.jp\/menu_img\/png_sp\/819259.png",
          "name" : "チキンカツカレー",
          "price" : "小385",
          "attr" : "d"
        },
        {
          "name" : "チキンカツカレー",
          "img" : "https:\/\/west2-univ.jp\/menu_img\/png_sp\/819259.png",
          "price" : "大495",
          "attr" : "d"
        },
        {
          "attr" : "d",
          "price" : "中319",
          "img" : "https:\/\/west2-univ.jp\/menu_img\/png_sp\/819272.png",
          "name" : "カレーライス"
        },
        {
          "price" : "中126",
          "name" : "ライス",
          "img" : "https:\/\/west2-univ.jp\/menu_img\/png_sp\/814702.png",
          "attr" : "d"
        },
        {
          "price" : "小105",
          "attr" : "d",
          "name" : "ライス",
          "img" : "https:\/\/west2-univ.jp\/menu_img\/png_sp\/814702.png"
        },
        {
          "attr" : "d",
          "img" : "https:\/\/west2-univ.jp\/menu_img\/png_sp\/814702.png",
          "price" : "大147",
          "name" : "ライス"
        }
      ]
    },
    {
      "name" : "Hokubu",
      "foods" : [
        {
          "price" : "176",
          "attr" : "e",
          "name" : "ストロベリーショート",
          "img" : "https:\/\/west2-univ.jp\/menu_img\/png_sp\/814843.png"
        },
        {
          "attr" : "e",
          "img" : "https:\/\/west2-univ.jp\/menu_img\/png_sp\/814808.png",
          "name" : "フルーツヨーグルト",
          "price" : "132"
        },
        {
          "price" : "110",
          "img" : "https:\/\/west2-univ.jp\/menu_img\/png_sp\/814851.png",
          "attr" : "e",
          "name" : "北海道いももち"
        },
        {
          "attr" : "e",
          "img" : "https:\/\/west2-univ.jp\/menu_img\/png_sp\/814816.png",
          "price" : "98",
          "name" : "牛乳"
        },
        {
          "attr" : "e",
          "img" : "https:\/\/west2-univ.jp\/menu_img\/png_sp\/814818.png",
          "price" : "105",
          "name" : "大学生協コーヒー"
        }
      ]
    },
    {
      "name" : "Hokubu",
      "foods" : [
        {
          "img" : "https:\/\/west2-univ.jp\/menu_img\/png_sp\/650118_449079.png",
          "price" : "572",
          "name" : "豚生姜焼き丼",
          "attr" : "1"
        }
      ]
    },
    {
      "name" : "Hokubu",
      "foods" : [
        {
          "price" : "572",
          "img" : "https:\/\/west2-univ.jp\/menu_img\/png_sp\/650118_449079.png",
          "attr" : "2",
          "name" : "豚生姜焼き丼"
        },
        {
          "attr" : "2",
          "img" : "https:\/\/west2-univ.jp\/menu_img\/png_sp\/819010.png",
          "name" : "牛クッパ中",
          "price" : "440"
        }
      ]
    },
    {
      "name" : "Nambu",
      "foods" : [
        {
          "img" : "https:\/\/west2-univ.jp\/menu_img\/png_sp\/814282.png",
          "name" : "ジューシー鶏カツソースあんかけ",
          "attr" : "a",
          "price" : "374"
        },
        {
          "price" : "286",
          "name" : "照りタルハンバーグ",
          "img" : "https:\/\/west2-univ.jp\/menu_img\/png_sp\/814055.png",
          "attr" : "a"
        },
        {
          "name" : "鶏醤油ちゃんこ煮",
          "price" : "286",
          "attr" : "a",
          "img" : "https:\/\/west2-univ.jp\/menu_img\/png_sp\/814021.png"
        },
        {
          "price" : "242",
          "name" : "海老よせフライ",
          "img" : "https:\/\/west2-univ.jp\/menu_img\/png_sp\/814309.png",
          "attr" : "a"
        },
        {
          "img" : "https:\/\/west2-univ.jp\/menu_img\/png_sp\/814314.png",
          "price" : "242",
          "name" : "ブリの甘酢あん",
          "attr" : "a"
        }
      ]
    },
    {
      "name" : "Nambu",
      "foods" : [
        {
          "name" : "納豆",
          "price" : "55",
          "img" : "https:\/\/west2-univ.jp\/menu_img\/png_sp\/814457.png",
          "attr" : "b"
        },
        {
          "img" : "https:\/\/west2-univ.jp\/menu_img\/png_sp\/814409.png",
          "price" : "121",
          "attr" : "b",
          "name" : "南瓜コロッケ"
        },
        {
          "name" : "スライスオクラ",
          "price" : "77",
          "img" : "https:\/\/west2-univ.jp\/menu_img\/png_sp\/814454.png",
          "attr" : "b"
        },
        {
          "attr" : "b",
          "name" : "茄子のピリ辛胡麻風味",
          "price" : "99",
          "img" : "https:\/\/west2-univ.jp\/menu_img\/png_sp\/814554.png"
        },
        {
          "price" : "99",
          "attr" : "b",
          "img" : "https:\/\/west2-univ.jp\/menu_img\/png_sp\/814539.png",
          "name" : "竹の子土佐煮"
        },
        {
          "name" : "春雨しそサラダ",
          "price" : "99",
          "img" : "https:\/\/west2-univ.jp\/menu_img\/png_sp\/814477.png",
          "attr" : "b"
        },
        {
          "attr" : "b",
          "price" : "99",
          "name" : "ほうれん草ごまナムル",
          "img" : "https:\/\/west2-univ.jp\/menu_img\/png_sp\/814578.png"
        },
        {
          "price" : "77",
          "img" : "https:\/\/west2-univ.jp\/menu_img\/png_sp\/814434.png",
          "attr" : "b",
          "name" : "ほうれん草"
        },
        {
          "price" : "55",
          "name" : "温泉玉子",
          "img" : "https:\/\/west2-univ.jp\/menu_img\/png_sp\/814456.png",
          "attr" : "b"
        },
        {
          "price" : "121",
          "img" : "https:\/\/west2-univ.jp\/menu_img\/png_sp\/814667.png",
          "name" : "豚汁",
          "attr" : "b"
        },
        {
          "name" : "味噌汁",
          "price" : "44",
          "img" : "https:\/\/west2-univ.jp\/menu_img\/png_sp\/814666.png",
          "attr" : "b"
        }
      ]
    },
    {
      "foods" : [
        {
          "name" : "ダッカルビ風野菜炒め",
          "price" : "286",
          "img" : "https:\/\/west2-univ.jp\/menu_img\/png_sp\/814257.png",
          "attr" : "a"
        },
        {
          "price" : "286",
          "img" : "https:\/\/west2-univ.jp\/menu_img\/png_sp\/814079.png",
          "name" : "麻婆茄子",
          "attr" : "a"
        },
        {
          "attr" : "a",
          "img" : "https:\/\/west2-univ.jp\/menu_img\/png_sp\/814309.png",
          "price" : "242",
          "name" : "海老よせフライ"
        },
        {
          "img" : "https:\/\/west2-univ.jp\/menu_img\/png_sp\/814314.png",
          "price" : "242",
          "name" : "ブリの甘酢あん",
          "attr" : "a"
        },
        {
          "name" : "豚と野菜の生姜炒め",
          "price" : "286",
          "img" : "https:\/\/west2-univ.jp\/menu_img\/png_sp\/814260.png",
          "attr" : "a"
        },
        {
          "price" : "286",
          "attr" : "a",
          "img" : "https:\/\/west2-univ.jp\/menu_img\/png_sp\/814049.png",
          "name" : "クラムチャウダー"
        },
        {
          "price" : "286",
          "attr" : "a",
          "img" : "https:\/\/west2-univ.jp\/menu_img\/png_sp\/814256.png",
          "name" : "鶏のチリソース炒め"
        },
        {
          "img" : "https:\/\/west2-univ.jp\/menu_img\/png_sp\/814021.png",
          "price" : "286",
          "attr" : "a",
          "name" : "鶏醤油ちゃんこ煮"
        },
        {
          "price" : "286",
          "img" : "https:\/\/west2-univ.jp\/menu_img\/png_sp\/814261.png",
          "name" : "豚もやし炒め",
          "attr" : "a"
        },
        {
          "price" : "286",
          "name" : "ビーフシチュー",
          "attr" : "a",
          "img" : "https:\/\/west2-univ.jp\/menu_img\/png_sp\/814126.png"
        },
        {
          "price" : "330",
          "name" : "Ｅジューシー鶏カツソースあんかけ",
          "attr" : "a",
          "img" : "https:\/\/west2-univ.jp\/menu_img\/png_sp\/824282.png"
        },
        {
          "img" : "https:\/\/west2-univ.jp\/menu_img\/png_sp\/824038.png",
          "price" : "242",
          "name" : "Ｅ唐揚げ香味ソース",
          "attr" : "a"
        },
        {
          "img" : "https:\/\/west2-univ.jp\/menu_img\/png_sp\/824012.png",
          "name" : "Ｅササミチーズタルタルソース",
          "price" : "242",
          "attr" : "a"
        },
        {
          "price" : "286",
          "name" : "Ｅローストチキン",
          "img" : "https:\/\/west2-univ.jp\/menu_img\/png_sp\/824005.png",
          "attr" : "a"
        },
        {
          "attr" : "a",
          "img" : "https:\/\/west2-univ.jp\/menu_img\/png_sp\/824085.png",
          "name" : "Ｅチキンカツチリソース",
          "price" : "242"
        },
        {
          "attr" : "a",
          "img" : "https:\/\/west2-univ.jp\/menu_img\/png_sp\/824311.png",
          "name" : "Eローストンカツ玉子あんかけ",
          "price" : "286"
        },
        {
          "price" : "286",
          "name" : "Ｅローストンカツごまソース",
          "img" : "https:\/\/west2-univ.jp\/menu_img\/png_sp\/824040.png",
          "attr" : "a"
        },
        {
          "name" : "Ｅローストンカツおろしソース",
          "attr" : "a",
          "price" : "286",
          "img" : "https:\/\/west2-univ.jp\/menu_img\/png_sp\/824022.png"
        },
        {
          "price" : "242",
          "img" : "https:\/\/west2-univ.jp\/menu_img\/png_sp\/824274.png",
          "attr" : "a",
          "name" : "Ｅポークミンチカツ"
        },
        {
          "price" : "242",
          "img" : "https:\/\/west2-univ.jp\/menu_img\/png_sp\/824055.png",
          "name" : "Ｅ照りタルハンバーグ",
          "attr" : "a"
        }
      ],
      "name" : "Bistro"
    },
    {
      "foods" : [
        {
          "img" : "https:\/\/west2-univ.jp\/menu_img\/png_sp\/814418.png",
          "name" : "ポテト野菜サラダ",
          "attr" : "b",
          "price" : "121"
        },
        {
          "name" : "南瓜コロッケ",
          "img" : "https:\/\/west2-univ.jp\/menu_img\/png_sp\/814409.png",
          "attr" : "b",
          "price" : "121"
        },
        {
          "price" : "99",
          "name" : "オクラ巣ごもり玉子",
          "img" : "https:\/\/west2-univ.jp\/menu_img\/png_sp\/814447.png",
          "attr" : "b"
        },
        {
          "price" : "99",
          "name" : "茄子のピリ辛胡麻風味",
          "attr" : "b",
          "img" : "https:\/\/west2-univ.jp\/menu_img\/png_sp\/814554.png"
        },
        {
          "name" : "竹の子土佐煮",
          "attr" : "b",
          "price" : "99",
          "img" : "https:\/\/west2-univ.jp\/menu_img\/png_sp\/814539.png"
        },
        {
          "img" : "https:\/\/west2-univ.jp\/menu_img\/png_sp\/814477.png",
          "attr" : "b",
          "price" : "99",
          "name" : "春雨しそサラダ"
        },
        {
          "name" : "ほうれん草ごまナムル",
          "img" : "https:\/\/west2-univ.jp\/menu_img\/png_sp\/814578.png",
          "price" : "99",
          "attr" : "b"
        },
        {
          "img" : "https:\/\/west2-univ.jp\/menu_img\/png_sp\/814434.png",
          "price" : "77",
          "name" : "ほうれん草",
          "attr" : "b"
        },
        {
          "price" : "77",
          "img" : "https:\/\/west2-univ.jp\/menu_img\/png_sp\/814453.png",
          "attr" : "b",
          "name" : "だし巻き"
        },
        {
          "attr" : "b",
          "name" : "きんぴらごぼう",
          "img" : "https:\/\/west2-univ.jp\/menu_img\/png_sp\/814552.png",
          "price" : "77"
        },
        {
          "price" : "77",
          "img" : "https:\/\/west2-univ.jp\/menu_img\/png_sp\/814454.png",
          "name" : "スライスオクラ",
          "attr" : "b"
        },
        {
          "name" : "冷奴",
          "attr" : "b",
          "price" : "55",
          "img" : "https:\/\/west2-univ.jp\/menu_img\/png_sp\/814455.png"
        },
        {
          "attr" : "b",
          "name" : "ミニサラダ",
          "price" : "55",
          "img" : "https:\/\/west2-univ.jp\/menu_img\/png_sp\/814460.png"
        },
        {
          "attr" : "b",
          "img" : "https:\/\/west2-univ.jp\/menu_img\/png_sp\/814667.png",
          "name" : "豚汁",
          "price" : "121"
        },
        {
          "name" : "味噌汁",
          "img" : "https:\/\/west2-univ.jp\/menu_img\/png_sp\/814666.png",
          "price" : "44",
          "attr" : "b"
        }
      ],
      "name" : "Bistro"
    },
    {
      "name" : "Bistro",
      "foods" : [
        {
          "name" : "パイタンうどん",
          "attr" : "c",
          "img" : "https:\/\/west2-univ.jp\/menu_img\/png_sp\/819362.png",
          "price" : "396"
        },
        {
          "attr" : "c",
          "name" : "温玉ぶっかけうどん",
          "img" : "https:\/\/west2-univ.jp\/menu_img\/png_sp\/819316.png",
          "price" : "352"
        },
        {
          "img" : "https:\/\/west2-univ.jp\/menu_img\/png_sp\/819317.png",
          "price" : "352",
          "attr" : "c",
          "name" : "温玉ぶっかけそば"
        },
        {
          "attr" : "c",
          "name" : "きつねうどん",
          "img" : "https:\/\/west2-univ.jp\/menu_img\/png_sp\/819393.png",
          "price" : "352"
        },
        {
          "name" : "きつねそば",
          "price" : "352",
          "attr" : "c",
          "img" : "https:\/\/west2-univ.jp\/menu_img\/png_sp\/819394.png"
        },
        {
          "name" : "かけうどん",
          "price" : "264",
          "attr" : "c",
          "img" : "https:\/\/west2-univ.jp\/menu_img\/png_sp\/819328.png"
        },
        {
          "attr" : "c",
          "img" : "https:\/\/west2-univ.jp\/menu_img\/png_sp\/819329.png",
          "price" : "264",
          "name" : "かけそば"
        },
        {
          "price" : "462",
          "img" : "https:\/\/west2-univ.jp\/menu_img\/png_sp\/819445.png",
          "attr" : "c",
          "name" : "醤油豚骨ラーメン"
        }
      ]
    },
    {
      "name" : "Bistro",
      "foods" : [
        {
          "img" : "https:\/\/west2-univ.jp\/menu_img\/png_sp\/819232.png",
          "name" : "サーモンビビンバ丼",
          "price" : "中495",
          "attr" : "d"
        },
        {
          "attr" : "d",
          "price" : "小440",
          "name" : "サーモンビビンバ丼",
          "img" : "https:\/\/west2-univ.jp\/menu_img\/png_sp\/819232.png"
        },
        {
          "img" : "https:\/\/west2-univ.jp\/menu_img\/png_sp\/819232.png",
          "price" : "大550",
          "name" : "サーモンビビンバ丼",
          "attr" : "d"
        },
        {
          "img" : "https:\/\/west2-univ.jp\/menu_img\/png_sp\/819951.png",
          "price" : "中440",
          "attr" : "d",
          "name" : "そぼろ親子丼"
        },
        {
          "img" : "https:\/\/west2-univ.jp\/menu_img\/png_sp\/819951.png",
          "attr" : "d",
          "name" : "そぼろ親子丼",
          "price" : "小385"
        },
        {
          "img" : "https:\/\/west2-univ.jp\/menu_img\/png_sp\/819951.png",
          "price" : "大495",
          "attr" : "d",
          "name" : "そぼろ親子丼"
        },
        {
          "img" : "https:\/\/west2-univ.jp\/menu_img\/png_sp\/819223.png",
          "attr" : "d",
          "price" : "中440",
          "name" : "唐揚げ茶漬け丼"
        },
        {
          "img" : "https:\/\/west2-univ.jp\/menu_img\/png_sp\/819223.png",
          "attr" : "d",
          "price" : "小385",
          "name" : "唐揚げ茶漬け丼"
        },
        {
          "name" : "唐揚げ茶漬け丼",
          "price" : "大495",
          "attr" : "d",
          "img" : "https:\/\/west2-univ.jp\/menu_img\/png_sp\/819223.png"
        },
        {
          "img" : "https:\/\/west2-univ.jp\/menu_img\/png_sp\/819256.png",
          "price" : "中440",
          "name" : "唐揚げカレー",
          "attr" : "d"
        },
        {
          "price" : "小385",
          "attr" : "d",
          "name" : "唐揚げカレー",
          "img" : "https:\/\/west2-univ.jp\/menu_img\/png_sp\/819256.png"
        },
        {
          "attr" : "d",
          "name" : "唐揚げカレー",
          "img" : "https:\/\/west2-univ.jp\/menu_img\/png_sp\/819256.png",
          "price" : "大495"
        },
        {
          "attr" : "d",
          "img" : "https:\/\/west2-univ.jp\/menu_img\/png_sp\/819272.png",
          "price" : "中319",
          "name" : "カレーライス"
        },
        {
          "img" : "https:\/\/west2-univ.jp\/menu_img\/png_sp\/819272.png",
          "attr" : "d",
          "price" : "小264",
          "name" : "カレーライス"
        },
        {
          "price" : "大374",
          "name" : "カレーライス",
          "attr" : "d",
          "img" : "https:\/\/west2-univ.jp\/menu_img\/png_sp\/819272.png"
        },
        {
          "img" : "https:\/\/west2-univ.jp\/menu_img\/png_sp\/814702.png",
          "price" : "中126",
          "attr" : "d",
          "name" : "ライス"
        },
        {
          "attr" : "d",
          "name" : "ライス",
          "price" : "小105",
          "img" : "https:\/\/west2-univ.jp\/menu_img\/png_sp\/814702.png"
        },
        {
          "img" : "https:\/\/west2-univ.jp\/menu_img\/png_sp\/814702.png",
          "attr" : "d",
          "name" : "ライス",
          "price" : "大147"
        }
      ]
    },
    {
      "name" : "Bistro",
      "foods" : [
        {
          "price" : "176",
          "attr" : "e",
          "name" : "ミルクティーショート",
          "img" : "https:\/\/west2-univ.jp\/menu_img\/png_sp\/814841.png"
        },
        {
          "img" : "https:\/\/west2-univ.jp\/menu_img\/png_sp\/814808.png",
          "price" : "132",
          "name" : "フルーツヨーグルト",
          "attr" : "e"
        },
        {
          "name" : "バナナクレープ",
          "price" : "88",
          "img" : "https:\/\/west2-univ.jp\/menu_img\/png_sp\/814890.png",
          "attr" : "e"
        },
        {
          "img" : "https:\/\/west2-univ.jp\/menu_img\/png_sp\/814817.png",
          "name" : "大学芋",
          "attr" : "e",
          "price" : "110"
        },
        {
          "price" : "98",
          "attr" : "e",
          "img" : "https:\/\/west2-univ.jp\/menu_img\/png_sp\/814816.png",
          "name" : "牛乳"
        }
      ]
    },
    {
      "foods" : [

      ],
      "name" : "Bistro"
    },
    {
      "foods" : [

      ],
      "name" : "Bistro"
    },
    {
      "name" : "Chuo",
      "foods" : [
        {
          "price" : "330",
          "attr" : "a",
          "name" : "ローストンカツポン酢おろし",
          "img" : "https:\/\/west2-univ.jp\/menu_img\/png_sp\/814042.png"
        },
        {
          "attr" : "a",
          "name" : "照りタルハンバーグ",
          "img" : "https:\/\/west2-univ.jp\/menu_img\/png_sp\/814055.png",
          "price" : "286"
        },
        {
          "img" : "https:\/\/west2-univ.jp\/menu_img\/png_sp\/814260.png",
          "name" : "豚と野菜の生姜炒め",
          "price" : "286",
          "attr" : "a"
        },
        {
          "attr" : "a",
          "price" : "286",
          "name" : "鶏醤油ちゃんこ煮",
          "img" : "https:\/\/west2-univ.jp\/menu_img\/png_sp\/814021.png"
        },
        {
          "name" : "チキンカツチリソース",
          "img" : "https:\/\/west2-univ.jp\/menu_img\/png_sp\/814085.png",
          "price" : "286",
          "attr" : "a"
        },
        {
          "name" : "タコキャベツカツ",
          "img" : "https:\/\/west2-univ.jp\/menu_img\/png_sp\/814292.png",
          "price" : "198",
          "attr" : "a"
        },
        {
          "img" : "https:\/\/west2-univ.jp\/menu_img\/png_sp\/814314.png",
          "attr" : "a",
          "price" : "242",
          "name" : "ブリの甘酢あん"
        }
      ]
    },
    {
      "foods" : [
        {
          "price" : "121",
          "attr" : "b",
          "name" : "牛肉コロッケ",
          "img" : "https:\/\/west2-univ.jp\/menu_img\/png_sp\/814403.png"
        },
        {
          "attr" : "b",
          "name" : "豆たっぷりヘルシーサラダ",
          "img" : "https:\/\/west2-univ.jp\/menu_img\/png_sp\/814506.png",
          "price" : "77"
        },
        {
          "attr" : "b",
          "name" : "千切り煮",
          "price" : "77",
          "img" : "https:\/\/west2-univ.jp\/menu_img\/png_sp\/814577.png"
        },
        {
          "name" : "蒸し鶏とオクラのゆず味噌",
          "img" : "https:\/\/west2-univ.jp\/menu_img\/png_sp\/814527.png",
          "attr" : "b",
          "price" : "99"
        },
        {
          "price" : "99",
          "img" : "https:\/\/west2-univ.jp\/menu_img\/png_sp\/814477.png",
          "name" : "春雨しそサラダ",
          "attr" : "b"
        },
        {
          "img" : "https:\/\/west2-univ.jp\/menu_img\/png_sp\/814539.png",
          "price" : "99",
          "name" : "竹の子土佐煮",
          "attr" : "b"
        },
        {
          "img" : "https:\/\/west2-univ.jp\/menu_img\/png_sp\/814434.png",
          "name" : "ほうれん草",
          "attr" : "b",
          "price" : "77"
        },
        {
          "name" : "温泉玉子",
          "attr" : "b",
          "price" : "55",
          "img" : "https:\/\/west2-univ.jp\/menu_img\/png_sp\/814456.png"
        },
        {
          "name" : "納豆",
          "price" : "55",
          "img" : "https:\/\/west2-univ.jp\/menu_img\/png_sp\/814457.png",
          "attr" : "b"
        },
        {
          "img" : "https:\/\/west2-univ.jp\/menu_img\/png_sp\/814667.png",
          "price" : "121",
          "attr" : "b",
          "name" : "豚汁"
        },
        {
          "img" : "https:\/\/west2-univ.jp\/menu_img\/png_sp\/814666.png",
          "attr" : "b",
          "name" : "味噌汁",
          "price" : "44"
        }
      ],
      "name" : "Chuo"
    },
    {
      "foods" : [
        {
          "name" : "温玉ぶっかけうどん",
          "img" : "https:\/\/west2-univ.jp\/menu_img\/png_sp\/819316.png",
          "attr" : "c",
          "price" : "352"
        },
        {
          "price" : "352",
          "name" : "温玉ぶっかけそば",
          "img" : "https:\/\/west2-univ.jp\/menu_img\/png_sp\/819317.png",
          "attr" : "c"
        },
        {
          "img" : "https:\/\/west2-univ.jp\/menu_img\/png_sp\/819393.png",
          "attr" : "c",
          "price" : "352",
          "name" : "きつねうどん"
        },
        {
          "price" : "352",
          "name" : "きつねそば",
          "img" : "https:\/\/west2-univ.jp\/menu_img\/png_sp\/819394.png",
          "attr" : "c"
        },
        {
          "price" : "264",
          "name" : "かけうどん",
          "attr" : "c",
          "img" : "https:\/\/west2-univ.jp\/menu_img\/png_sp\/819328.png"
        },
        {
          "attr" : "c",
          "price" : "264",
          "name" : "かけそば",
          "img" : "https:\/\/west2-univ.jp\/menu_img\/png_sp\/819329.png"
        }
      ],
      "name" : "Chuo"
    },
    {
      "name" : "Chuo",
      "foods" : [
        {
          "img" : "https:\/\/west2-univ.jp\/menu_img\/png_sp\/650118_446040.png",
          "attr" : "d",
          "name" : "サーモン炙りハラス丼",
          "price" : "中495"
        },
        {
          "attr" : "d",
          "img" : "https:\/\/west2-univ.jp\/menu_img\/png_sp\/814702.png",
          "price" : "中126",
          "name" : "ライス"
        },
        {
          "img" : "https:\/\/west2-univ.jp\/menu_img\/png_sp\/814702.png",
          "name" : "ライス",
          "price" : "ﾐﾆ84",
          "attr" : "d"
        },
        {
          "img" : "https:\/\/west2-univ.jp\/menu_img\/png_sp\/814702.png",
          "name" : "ライス",
          "price" : "小105",
          "attr" : "d"
        },
        {
          "name" : "ライス",
          "attr" : "d",
          "img" : "https:\/\/west2-univ.jp\/menu_img\/png_sp\/814702.png",
          "price" : "大147"
        }
      ]
    },
    {
      "foods" : [
        {
          "name" : "バナナクレープ",
          "price" : "88",
          "img" : "https:\/\/west2-univ.jp\/menu_img\/png_sp\/814890.png",
          "attr" : "e"
        },
        {
          "attr" : "e",
          "img" : "https:\/\/west2-univ.jp\/menu_img\/png_sp\/814808.png",
          "price" : "132",
          "name" : "フルーツヨーグルト"
        },
        {
          "price" : "98",
          "img" : "https:\/\/west2-univ.jp\/menu_img\/png_sp\/814816.png",
          "attr" : "e",
          "name" : "牛乳"
        },
        {
          "price" : "105",
          "name" : "大学生協コーヒー",
          "attr" : "e",
          "img" : "https:\/\/west2-univ.jp\/menu_img\/png_sp\/814818.png"
        }
      ],
      "name" : "Chuo"
    },
    {
      "foods" : [
        {
          "price" : "374",
          "img" : "https:\/\/west2-univ.jp\/menu_img\/png_sp\/650118_446140.png",
          "name" : "名古屋風唐揚げ",
          "attr" : "2"
        }
      ],
      "name" : "Chuo"
    },
    {
      "foods" : [
        {
          "attr" : "a",
          "img" : "https:\/\/west2-univ.jp\/menu_img\/png_sp\/814021.png",
          "price" : "286",
          "name" : "鶏醤油ちゃんこ煮"
        },
        {
          "img" : "https:\/\/west2-univ.jp\/menu_img\/png_sp\/814309.png",
          "price" : "242",
          "attr" : "a",
          "name" : "海老よせフライ"
        },
        {
          "img" : "https:\/\/west2-univ.jp\/menu_img\/png_sp\/814314.png",
          "name" : "ブリの甘酢あん",
          "attr" : "a",
          "price" : "242"
        },
        {
          "attr" : "a",
          "price" : "330",
          "img" : "https:\/\/west2-univ.jp\/menu_img\/png_sp\/824282.png",
          "name" : "Ｅジューシー鶏カツソースあんかけ"
        },
        {
          "img" : "https:\/\/west2-univ.jp\/menu_img\/png_sp\/824022.png",
          "attr" : "a",
          "name" : "Ｅローストンカツおろしソース",
          "price" : "286"
        },
        {
          "attr" : "a",
          "name" : "Ｅチキンカツチリソース",
          "price" : "242",
          "img" : "https:\/\/west2-univ.jp\/menu_img\/png_sp\/824085.png"
        },
        {
          "img" : "https:\/\/west2-univ.jp\/menu_img\/png_sp\/824055.png",
          "price" : "242",
          "name" : "Ｅ照りタルハンバーグ",
          "attr" : "a"
        }
      ],
      "name" : "Ortus"
    },
    {
      "name" : "Ortus",
      "foods" : [
        {
          "price" : "121",
          "img" : "https:\/\/west2-univ.jp\/menu_img\/png_sp\/814418.png",
          "attr" : "b",
          "name" : "ポテト野菜サラダ"
        },
        {
          "name" : "南瓜コロッケ",
          "attr" : "b",
          "price" : "121",
          "img" : "https:\/\/west2-univ.jp\/menu_img\/png_sp\/814409.png"
        },
        {
          "price" : "99",
          "name" : "オクラ巣ごもり玉子",
          "img" : "https:\/\/west2-univ.jp\/menu_img\/png_sp\/814447.png",
          "attr" : "b"
        },
        {
          "attr" : "b",
          "price" : "99",
          "name" : "鶏きも煮",
          "img" : "https:\/\/west2-univ.jp\/menu_img\/png_sp\/814524.png"
        },
        {
          "img" : "https:\/\/west2-univ.jp\/menu_img\/png_sp\/814539.png",
          "name" : "竹の子土佐煮",
          "attr" : "b",
          "price" : "99"
        },
        {
          "name" : "春雨しそサラダ",
          "attr" : "b",
          "price" : "99",
          "img" : "https:\/\/west2-univ.jp\/menu_img\/png_sp\/814477.png"
        },
        {
          "name" : "ほうれん草ごまナムル",
          "img" : "https:\/\/west2-univ.jp\/menu_img\/png_sp\/814578.png",
          "price" : "99",
          "attr" : "b"
        },
        {
          "attr" : "b",
          "name" : "ほうれん草",
          "img" : "https:\/\/west2-univ.jp\/menu_img\/png_sp\/814434.png",
          "price" : "77"
        },
        {
          "name" : "だし巻き",
          "img" : "https:\/\/west2-univ.jp\/menu_img\/png_sp\/814453.png",
          "price" : "77",
          "attr" : "b"
        },
        {
          "attr" : "b",
          "price" : "77",
          "name" : "きんぴらごぼう",
          "img" : "https:\/\/west2-univ.jp\/menu_img\/png_sp\/814552.png"
        },
        {
          "name" : "スライスオクラ",
          "price" : "77",
          "img" : "https:\/\/west2-univ.jp\/menu_img\/png_sp\/814454.png",
          "attr" : "b"
        },
        {
          "price" : "55",
          "attr" : "b",
          "name" : "冷奴",
          "img" : "https:\/\/west2-univ.jp\/menu_img\/png_sp\/814455.png"
        },
        {
          "img" : "https:\/\/west2-univ.jp\/menu_img\/png_sp\/814460.png",
          "attr" : "b",
          "price" : "55",
          "name" : "ミニサラダ"
        },
        {
          "name" : "豚汁",
          "img" : "https:\/\/west2-univ.jp\/menu_img\/png_sp\/814667.png",
          "attr" : "b",
          "price" : "121"
        },
        {
          "price" : "44",
          "attr" : "b",
          "name" : "味噌汁",
          "img" : "https:\/\/west2-univ.jp\/menu_img\/png_sp\/814666.png"
        },
        {
          "attr" : "b",
          "name" : "納豆",
          "img" : "https:\/\/west2-univ.jp\/menu_img\/png_sp\/814457.png",
          "price" : "55"
        }
      ]
    },
    {
      "name" : "Ortus",
      "foods" : [
        {
          "img" : "https:\/\/west2-univ.jp\/menu_img\/png_sp\/819362.png",
          "attr" : "c",
          "price" : "396",
          "name" : "パイタンうどん"
        },
        {
          "attr" : "c",
          "name" : "温玉ぶっかけうどん",
          "img" : "https:\/\/west2-univ.jp\/menu_img\/png_sp\/819316.png",
          "price" : "352"
        },
        {
          "name" : "温玉ぶっかけそば",
          "img" : "https:\/\/west2-univ.jp\/menu_img\/png_sp\/819317.png",
          "attr" : "c",
          "price" : "352"
        },
        {
          "attr" : "c",
          "img" : "https:\/\/west2-univ.jp\/menu_img\/png_sp\/819393.png",
          "name" : "きつねうどん",
          "price" : "352"
        },
        {
          "name" : "きつねそば",
          "price" : "352",
          "attr" : "c",
          "img" : "https:\/\/west2-univ.jp\/menu_img\/png_sp\/819394.png"
        },
        {
          "price" : "264",
          "attr" : "c",
          "name" : "かけうどん",
          "img" : "https:\/\/west2-univ.jp\/menu_img\/png_sp\/819328.png"
        },
        {
          "price" : "264",
          "name" : "かけそば",
          "img" : "https:\/\/west2-univ.jp\/menu_img\/png_sp\/819329.png",
          "attr" : "c"
        },
        {
          "img" : "https:\/\/west2-univ.jp\/menu_img\/png_sp\/819445.png",
          "name" : "醤油豚骨ラーメン",
          "attr" : "c",
          "price" : "462"
        }
      ]
    },
    {
      "foods" : [
        {
          "attr" : "d",
          "img" : "https:\/\/west2-univ.jp\/menu_img\/png_sp\/819232.png",
          "name" : "サーモンビビンバ丼",
          "price" : "中495"
        },
        {
          "name" : "サーモンビビンバ丼",
          "price" : "小440",
          "attr" : "d",
          "img" : "https:\/\/west2-univ.jp\/menu_img\/png_sp\/819232.png"
        },
        {
          "img" : "https:\/\/west2-univ.jp\/menu_img\/png_sp\/819232.png",
          "price" : "大550",
          "name" : "サーモンビビンバ丼",
          "attr" : "d"
        },
        {
          "price" : "中440",
          "attr" : "d",
          "img" : "https:\/\/west2-univ.jp\/menu_img\/png_sp\/819951.png",
          "name" : "そぼろ親子丼"
        },
        {
          "price" : "小385",
          "attr" : "d",
          "name" : "そぼろ親子丼",
          "img" : "https:\/\/west2-univ.jp\/menu_img\/png_sp\/819951.png"
        },
        {
          "price" : "大495",
          "name" : "そぼろ親子丼",
          "attr" : "d",
          "img" : "https:\/\/west2-univ.jp\/menu_img\/png_sp\/819951.png"
        },
        {
          "img" : "https:\/\/west2-univ.jp\/menu_img\/png_sp\/819223.png",
          "price" : "中440",
          "attr" : "d",
          "name" : "唐揚げ茶漬け丼"
        },
        {
          "name" : "唐揚げ茶漬け丼",
          "price" : "小385",
          "img" : "https:\/\/west2-univ.jp\/menu_img\/png_sp\/819223.png",
          "attr" : "d"
        },
        {
          "name" : "唐揚げ茶漬け丼",
          "price" : "大495",
          "img" : "https:\/\/west2-univ.jp\/menu_img\/png_sp\/819223.png",
          "attr" : "d"
        },
        {
          "img" : "https:\/\/west2-univ.jp\/menu_img\/png_sp\/819256.png",
          "price" : "中440",
          "name" : "唐揚げカレー",
          "attr" : "d"
        },
        {
          "price" : "小385",
          "attr" : "d",
          "img" : "https:\/\/west2-univ.jp\/menu_img\/png_sp\/819256.png",
          "name" : "唐揚げカレー"
        },
        {
          "attr" : "d",
          "name" : "唐揚げカレー",
          "img" : "https:\/\/west2-univ.jp\/menu_img\/png_sp\/819256.png",
          "price" : "大495"
        },
        {
          "price" : "中319",
          "name" : "カレーライス",
          "attr" : "d",
          "img" : "https:\/\/west2-univ.jp\/menu_img\/png_sp\/819272.png"
        },
        {
          "price" : "小264",
          "attr" : "d",
          "img" : "https:\/\/west2-univ.jp\/menu_img\/png_sp\/819272.png",
          "name" : "カレーライス"
        },
        {
          "price" : "大374",
          "img" : "https:\/\/west2-univ.jp\/menu_img\/png_sp\/819272.png",
          "name" : "カレーライス",
          "attr" : "d"
        },
        {
          "attr" : "d",
          "name" : "ライス",
          "img" : "https:\/\/west2-univ.jp\/menu_img\/png_sp\/814702.png",
          "price" : "中126"
        },
        {
          "price" : "小105",
          "attr" : "d",
          "img" : "https:\/\/west2-univ.jp\/menu_img\/png_sp\/814702.png",
          "name" : "ライス"
        },
        {
          "img" : "https:\/\/west2-univ.jp\/menu_img\/png_sp\/814702.png",
          "name" : "ライス",
          "attr" : "d",
          "price" : "大147"
        }
      ],
      "name" : "Ortus"
    },
    {
      "name" : "Ortus",
      "foods" : [
        {
          "name" : "ミルクティーショート",
          "img" : "https:\/\/west2-univ.jp\/menu_img\/png_sp\/814841.png",
          "attr" : "e",
          "price" : "176"
        },
        {
          "name" : "フルーツヨーグルト",
          "attr" : "e",
          "price" : "132",
          "img" : "https:\/\/west2-univ.jp\/menu_img\/png_sp\/814808.png"
        },
        {
          "name" : "バナナクレープ",
          "price" : "88",
          "img" : "https:\/\/west2-univ.jp\/menu_img\/png_sp\/814890.png",
          "attr" : "e"
        }
      ]
    },
    {
      "foods" : [
        {
          "attr" : "a",
          "name" : "チキンカツカレーマヨ",
          "price" : "286",
          "img" : "https:\/\/west2-univ.jp\/menu_img\/png_sp\/814086.png"
        },
        {
          "name" : "照りタルハンバーグ",
          "img" : "https:\/\/west2-univ.jp\/menu_img\/png_sp\/814055.png",
          "price" : "286",
          "attr" : "a"
        },
        {
          "price" : "286",
          "attr" : "a",
          "img" : "https:\/\/west2-univ.jp\/menu_img\/png_sp\/814256.png",
          "name" : "鶏のチリソース炒め"
        },
        {
          "name" : "鶏醤油ちゃんこ煮",
          "attr" : "a",
          "price" : "286",
          "img" : "https:\/\/west2-univ.jp\/menu_img\/png_sp\/814021.png"
        },
        {
          "name" : "鯖味噌煮",
          "attr" : "a",
          "img" : "https:\/\/west2-univ.jp\/menu_img\/png_sp\/814297.png",
          "price" : "242"
        }
      ],
      "name" : "Katsura"
    },
    {
      "name" : "Katsura",
      "foods" : [
        {
          "attr" : "b",
          "img" : "https:\/\/west2-univ.jp\/menu_img\/png_sp\/814409.png",
          "price" : "121",
          "name" : "南瓜コロッケ"
        },
        {
          "img" : "https:\/\/west2-univ.jp\/menu_img\/png_sp\/650118_449933.png",
          "name" : "春雨中華サラダ",
          "attr" : "b",
          "price" : "99"
        },
        {
          "img" : "https:\/\/west2-univ.jp\/menu_img\/png_sp\/814552.png",
          "attr" : "b",
          "price" : "77",
          "name" : "きんぴらごぼう"
        },
        {
          "price" : "99",
          "img" : "https:\/\/west2-univ.jp\/menu_img\/png_sp\/814505.png",
          "name" : "さっぱり揚げ出し茄子",
          "attr" : "b"
        },
        {
          "price" : "99",
          "img" : "https:\/\/west2-univ.jp\/menu_img\/png_sp\/814578.png",
          "name" : "ほうれん草ごまナムル",
          "attr" : "b"
        },
        {
          "price" : "77",
          "name" : "ひじき煮",
          "img" : "https:\/\/west2-univ.jp\/menu_img\/png_sp\/814580.png",
          "attr" : "b"
        },
        {
          "name" : "スライスオクラ",
          "attr" : "b",
          "img" : "https:\/\/west2-univ.jp\/menu_img\/png_sp\/814454.png",
          "price" : "77"
        },
        {
          "name" : "冷奴",
          "price" : "55",
          "attr" : "b",
          "img" : "https:\/\/west2-univ.jp\/menu_img\/png_sp\/814455.png"
        },
        {
          "price" : "55",
          "attr" : "b",
          "img" : "https:\/\/west2-univ.jp\/menu_img\/png_sp\/814457.png",
          "name" : "納豆"
        },
        {
          "img" : "https:\/\/west2-univ.jp\/menu_img\/png_sp\/814667.png",
          "name" : "豚汁",
          "price" : "121",
          "attr" : "b"
        },
        {
          "img" : "https:\/\/west2-univ.jp\/menu_img\/png_sp\/814666.png",
          "name" : "味噌汁",
          "attr" : "b",
          "price" : "44"
        }
      ]
    },
    {
      "foods" : [
        {
          "price" : "352",
          "img" : "https:\/\/west2-univ.jp\/menu_img\/png_sp\/819312.png",
          "attr" : "c",
          "name" : "かき揚げうどん"
        },
        {
          "name" : "きつねうどん",
          "img" : "https:\/\/west2-univ.jp\/menu_img\/png_sp\/819393.png",
          "attr" : "c",
          "price" : "352"
        },
        {
          "attr" : "c",
          "price" : "264",
          "img" : "https:\/\/west2-univ.jp\/menu_img\/png_sp\/819328.png",
          "name" : "かけうどん"
        },
        {
          "attr" : "c",
          "name" : "醤油豚骨ラーメン",
          "img" : "https:\/\/west2-univ.jp\/menu_img\/png_sp\/819445.png",
          "price" : "462"
        }
      ],
      "name" : "Katsura"
    },
    {
      "foods" : [
        {
          "img" : "https:\/\/west2-univ.jp\/menu_img\/png_sp\/819232.png",
          "name" : "サーモンビビンバ丼",
          "attr" : "d",
          "price" : "中495"
        },
        {
          "price" : "小440",
          "attr" : "d",
          "img" : "https:\/\/west2-univ.jp\/menu_img\/png_sp\/819232.png",
          "name" : "サーモンビビンバ丼"
        },
        {
          "img" : "https:\/\/west2-univ.jp\/menu_img\/png_sp\/819232.png",
          "price" : "大550",
          "attr" : "d",
          "name" : "サーモンビビンバ丼"
        },
        {
          "attr" : "d",
          "img" : "https:\/\/west2-univ.jp\/menu_img\/png_sp\/819951.png",
          "name" : "そぼろ親子丼",
          "price" : "中440"
        },
        {
          "img" : "https:\/\/west2-univ.jp\/menu_img\/png_sp\/819951.png",
          "attr" : "d",
          "price" : "小385",
          "name" : "そぼろ親子丼"
        },
        {
          "attr" : "d",
          "img" : "https:\/\/west2-univ.jp\/menu_img\/png_sp\/819951.png",
          "price" : "大495",
          "name" : "そぼろ親子丼"
        },
        {
          "price" : "中440",
          "attr" : "d",
          "img" : "https:\/\/west2-univ.jp\/menu_img\/png_sp\/819223.png",
          "name" : "唐揚げ茶漬け丼"
        },
        {
          "img" : "https:\/\/west2-univ.jp\/menu_img\/png_sp\/819223.png",
          "name" : "唐揚げ茶漬け丼",
          "attr" : "d",
          "price" : "小385"
        },
        {
          "price" : "大495",
          "img" : "https:\/\/west2-univ.jp\/menu_img\/png_sp\/819223.png",
          "name" : "唐揚げ茶漬け丼",
          "attr" : "d"
        },
        {
          "name" : "唐揚げカレー",
          "attr" : "d",
          "price" : "中440",
          "img" : "https:\/\/west2-univ.jp\/menu_img\/png_sp\/819256.png"
        },
        {
          "img" : "https:\/\/west2-univ.jp\/menu_img\/png_sp\/819256.png",
          "name" : "唐揚げカレー",
          "attr" : "d",
          "price" : "小385"
        },
        {
          "img" : "https:\/\/west2-univ.jp\/menu_img\/png_sp\/819256.png",
          "attr" : "d",
          "price" : "大495",
          "name" : "唐揚げカレー"
        },
        {
          "name" : "カレーライス",
          "attr" : "d",
          "price" : "中319",
          "img" : "https:\/\/west2-univ.jp\/menu_img\/png_sp\/819272.png"
        },
        {
          "price" : "小264",
          "img" : "https:\/\/west2-univ.jp\/menu_img\/png_sp\/819272.png",
          "attr" : "d",
          "name" : "カレーライス"
        },
        {
          "attr" : "d",
          "price" : "大374",
          "name" : "カレーライス",
          "img" : "https:\/\/west2-univ.jp\/menu_img\/png_sp\/819272.png"
        },
        {
          "img" : "https:\/\/west2-univ.jp\/menu_img\/png_sp\/814702.png",
          "price" : "中126",
          "attr" : "d",
          "name" : "ライス"
        },
        {
          "attr" : "d",
          "img" : "https:\/\/west2-univ.jp\/menu_img\/png_sp\/814702.png",
          "price" : "小105",
          "name" : "ライス"
        },
        {
          "name" : "ライス",
          "attr" : "d",
          "img" : "https:\/\/west2-univ.jp\/menu_img\/png_sp\/814702.png",
          "price" : "大147"
        }
      ],
      "name" : "Katsura"
    },
    {
      "name" : "Katsura",
      "foods" : [
        {
          "attr" : "e",
          "name" : "フルーツヨーグルト",
          "img" : "https:\/\/west2-univ.jp\/menu_img\/png_sp\/814808.png",
          "price" : "132"
        },
        {
          "name" : "大学生協コーヒー",
          "price" : "105",
          "attr" : "e",
          "img" : "https:\/\/west2-univ.jp\/menu_img\/png_sp\/814818.png"
        },
        {
          "price" : "110",
          "name" : "大学芋",
          "attr" : "e",
          "img" : "https:\/\/west2-univ.jp\/menu_img\/png_sp\/814817.png"
        },
        {
          "price" : "98",
          "img" : "https:\/\/west2-univ.jp\/menu_img\/png_sp\/814816.png",
          "name" : "牛乳",
          "attr" : "e"
        }
      ]
    },
    {
      "name" : "Katsura",
      "foods" : [
        {
          "attr" : "1",
          "img" : "https:\/\/west2-univ.jp\/menu_img\/png_sp\/814082.png",
          "price" : "286",
          "name" : "チキンカツ柚子胡椒マヨ"
        }
      ]
    },
    {
      "name" : "Katsura",
      "foods" : [
        {
          "price" : "242",
          "attr" : "2",
          "img" : "https:\/\/west2-univ.jp\/menu_img\/png_sp\/814309.png",
          "name" : "海老よせフライ"
        }
      ]
    },
    {
      "name" : "Katsura",
      "foods" : [
        {
          "name" : "チキン南蛮",
          "img" : "https:\/\/west2-univ.jp\/menu_img\/png_sp\/814128.png",
          "attr" : "3",
          "price" : "374"
        },
        {
          "price" : "286",
          "name" : "ポークミンチカツ",
          "img" : "https:\/\/west2-univ.jp\/menu_img\/png_sp\/814274.png",
          "attr" : "3"
        },
        {
          "attr" : "3",
          "price" : "286",
          "img" : "https:\/\/west2-univ.jp\/menu_img\/png_sp\/814260.png",
          "name" : "豚と野菜の生姜炒め"
        },
        {
          "attr" : "3",
          "price" : "242",
          "name" : "鯖生姜煮",
          "img" : "https:\/\/west2-univ.jp\/menu_img\/png_sp\/814298.png"
        },
        {
          "attr" : "3",
          "img" : "https:\/\/west2-univ.jp\/menu_img\/png_sp\/814409.png",
          "price" : "121",
          "name" : "南瓜コロッケ"
        },
        {
          "attr" : "3",
          "img" : "https:\/\/west2-univ.jp\/menu_img\/png_sp\/650118_449939.png",
          "name" : "ごぼうとナッツのサラダ",
          "price" : "99"
        },
        {
          "img" : "https:\/\/west2-univ.jp\/menu_img\/png_sp\/650118_449933.png",
          "name" : "春雨中華サラダ",
          "price" : "99",
          "attr" : "3"
        },
        {
          "name" : "ブロッコーンバター醤油",
          "price" : "99",
          "attr" : "3",
          "img" : "https:\/\/west2-univ.jp\/menu_img\/png_sp\/814535.png"
        },
        {
          "attr" : "3",
          "img" : "https:\/\/west2-univ.jp\/menu_img\/png_sp\/814412.png",
          "price" : "99",
          "name" : "ねぎだくもやしナムル"
        },
        {
          "price" : "55",
          "img" : "https:\/\/west2-univ.jp\/menu_img\/png_sp\/814457.png",
          "name" : "納豆",
          "attr" : "3"
        },
        {
          "name" : "豚汁",
          "attr" : "3",
          "img" : "https:\/\/west2-univ.jp\/menu_img\/png_sp\/814667.png",
          "price" : "121"
        },
        {
          "img" : "https:\/\/west2-univ.jp\/menu_img\/png_sp\/814666.png",
          "name" : "味噌汁",
          "attr" : "3",
          "price" : "44"
        },
        {
          "price" : "132",
          "attr" : "3",
          "img" : "https:\/\/west2-univ.jp\/menu_img\/png_sp\/814808.png",
          "name" : "フルーツヨーグルト"
        },
        {
          "attr" : "3",
          "name" : "大学生協コーヒー",
          "price" : "105",
          "img" : "https:\/\/west2-univ.jp\/menu_img\/png_sp\/814818.png"
        },
        {
          "img" : "https:\/\/west2-univ.jp\/menu_img\/png_sp\/814816.png",
          "name" : "牛乳",
          "price" : "98",
          "attr" : "3"
        }
      ]
    },
    {
      "name" : "Uji",
      "foods" : [
        {
          "name" : "照りタルハンバーグ",
          "price" : "286",
          "img" : "https:\/\/west2-univ.jp\/menu_img\/png_sp\/814055.png",
          "attr" : "a"
        },
        {
          "attr" : "a",
          "img" : "https:\/\/west2-univ.jp\/menu_img\/png_sp\/814256.png",
          "name" : "鶏のチリソース炒め",
          "price" : "286"
        },
        {
          "name" : "鶏醤油ちゃんこ煮",
          "attr" : "a",
          "img" : "https:\/\/west2-univ.jp\/menu_img\/png_sp\/814021.png",
          "price" : "286"
        }
      ]
    },
    {
      "foods" : [
        {
          "img" : "https:\/\/west2-univ.jp\/menu_img\/png_sp\/814408.png",
          "price" : "121",
          "attr" : "b",
          "name" : "春巻き"
        },
        {
          "name" : "春雨中華サラダ",
          "img" : "https:\/\/west2-univ.jp\/menu_img\/png_sp\/650118_449933.png",
          "price" : "99",
          "attr" : "b"
        },
        {
          "img" : "https:\/\/west2-univ.jp\/menu_img\/png_sp\/814577.png",
          "attr" : "b",
          "price" : "77",
          "name" : "千切り煮"
        },
        {
          "img" : "https:\/\/west2-univ.jp\/menu_img\/png_sp\/814505.png",
          "attr" : "b",
          "price" : "99",
          "name" : "さっぱり揚げ出し茄子"
        },
        {
          "attr" : "b",
          "price" : "99",
          "name" : "ほうれん草ごまナムル",
          "img" : "https:\/\/west2-univ.jp\/menu_img\/png_sp\/814578.png"
        },
        {
          "name" : "スライスオクラ",
          "attr" : "b",
          "img" : "https:\/\/west2-univ.jp\/menu_img\/png_sp\/814454.png",
          "price" : "77"
        },
        {
          "name" : "ひじき煮",
          "price" : "77",
          "img" : "https:\/\/west2-univ.jp\/menu_img\/png_sp\/814580.png",
          "attr" : "b"
        },
        {
          "price" : "55",
          "name" : "冷奴",
          "img" : "https:\/\/west2-univ.jp\/menu_img\/png_sp\/814455.png",
          "attr" : "b"
        },
        {
          "name" : "納豆",
          "price" : "55",
          "img" : "https:\/\/west2-univ.jp\/menu_img\/png_sp\/814457.png",
          "attr" : "b"
        },
        {
          "name" : "豚汁",
          "img" : "https:\/\/west2-univ.jp\/menu_img\/png_sp\/814667.png",
          "price" : "121",
          "attr" : "b"
        },
        {
          "price" : "44",
          "name" : "味噌汁",
          "attr" : "b",
          "img" : "https:\/\/west2-univ.jp\/menu_img\/png_sp\/814666.png"
        }
      ],
      "name" : "Uji"
    },
    {
      "foods" : [
        {
          "img" : "https:\/\/west2-univ.jp\/menu_img\/png_sp\/650118_446040.png",
          "name" : "サーモン炙りハラス丼",
          "attr" : "d",
          "price" : "中495"
        },
        {
          "name" : "唐揚げカレー",
          "img" : "https:\/\/west2-univ.jp\/menu_img\/png_sp\/819256.png",
          "attr" : "d",
          "price" : "中440"
        },
        {
          "attr" : "d",
          "price" : "小385",
          "name" : "唐揚げカレー",
          "img" : "https:\/\/west2-univ.jp\/menu_img\/png_sp\/819256.png"
        },
        {
          "img" : "https:\/\/west2-univ.jp\/menu_img\/png_sp\/819256.png",
          "price" : "大495",
          "name" : "唐揚げカレー",
          "attr" : "d"
        },
        {
          "img" : "https:\/\/west2-univ.jp\/menu_img\/png_sp\/819272.png",
          "name" : "カレーライス",
          "price" : "中319",
          "attr" : "d"
        },
        {
          "img" : "https:\/\/west2-univ.jp\/menu_img\/png_sp\/819272.png",
          "attr" : "d",
          "price" : "小264",
          "name" : "カレーライス"
        },
        {
          "price" : "大374",
          "name" : "カレーライス",
          "img" : "https:\/\/west2-univ.jp\/menu_img\/png_sp\/819272.png",
          "attr" : "d"
        },
        {
          "price" : "中126",
          "name" : "ライス",
          "attr" : "d",
          "img" : "https:\/\/west2-univ.jp\/menu_img\/png_sp\/814702.png"
        },
        {
          "name" : "ライス",
          "img" : "https:\/\/west2-univ.jp\/menu_img\/png_sp\/814702.png",
          "attr" : "d",
          "price" : "小105"
        },
        {
          "name" : "ライス",
          "img" : "https:\/\/west2-univ.jp\/menu_img\/png_sp\/814702.png",
          "price" : "大147",
          "attr" : "d"
        }
      ],
      "name" : "Uji"
    },
    {
      "foods" : [
        {
          "name" : "フルーツヨーグルト",
          "img" : "https:\/\/west2-univ.jp\/menu_img\/png_sp\/814808.png",
          "price" : "132",
          "attr" : "e"
        },
        {
          "img" : "https:\/\/west2-univ.jp\/menu_img\/png_sp\/814817.png",
          "attr" : "e",
          "name" : "大学芋",
          "price" : "110"
        },
        {
          "img" : "https:\/\/west2-univ.jp\/menu_img\/png_sp\/814816.png",
          "name" : "牛乳",
          "attr" : "e",
          "price" : "98"
        }
      ],
      "name" : "Uji"
    },
    {
      "name" : "Uji",
      "foods" : [
        {
          "attr" : "1",
          "price" : "374",
          "img" : "https:\/\/west2-univ.jp\/menu_img\/png_sp\/814128.png",
          "name" : "チキン南蛮"
        }
      ]
    },
    {
      "foods" : [
        {
          "img" : "https:\/\/west2-univ.jp\/menu_img\/png_sp\/814082.png",
          "price" : "286",
          "name" : "チキンカツ柚子胡椒マヨ",
          "attr" : "2"
        }
      ],
      "name" : "Uji"
    },
    {
      "name" : "Uji",
      "foods" : [
        {
          "img" : "https:\/\/west2-univ.jp\/menu_img\/png_sp\/819951.png",
          "attr" : "3",
          "name" : "そぼろ親子丼中",
          "price" : "440"
        }
      ]
    },
    {
      "foods" : [
        {
          "price" : "374",
          "attr" : "a",
          "img" : "https:\/\/west2-univ.jp\/menu_img\/png_sp\/814282.png",
          "name" : "ジューシー鶏カツソースあんかけ"
        },
        {
          "name" : "ローストンカツおろしソース",
          "price" : "330",
          "img" : "https:\/\/west2-univ.jp\/menu_img\/png_sp\/814022.png",
          "attr" : "a"
        },
        {
          "img" : "https:\/\/west2-univ.jp\/menu_img\/png_sp\/814085.png",
          "price" : "286",
          "attr" : "a",
          "name" : "チキンカツチリソース"
        },
        {
          "img" : "https:\/\/west2-univ.jp\/menu_img\/png_sp\/814055.png",
          "name" : "照りタルハンバーグ",
          "price" : "286",
          "attr" : "a"
        },
        {
          "price" : "286",
          "attr" : "a",
          "name" : "鶏のチリソース炒め",
          "img" : "https:\/\/west2-univ.jp\/menu_img\/png_sp\/814256.png"
        },
        {
          "name" : "鶏醤油ちゃんこ煮",
          "price" : "286",
          "img" : "https:\/\/west2-univ.jp\/menu_img\/png_sp\/814021.png",
          "attr" : "a"
        },
        {
          "attr" : "a",
          "name" : "海老よせフライ",
          "price" : "242",
          "img" : "https:\/\/west2-univ.jp\/menu_img\/png_sp\/814309.png"
        },
        {
          "attr" : "a",
          "price" : "242",
          "img" : "https:\/\/west2-univ.jp\/menu_img\/png_sp\/814314.png",
          "name" : "ブリの甘酢あん"
        }
      ],
      "name" : "Kyoyu"
    },
    {
      "foods" : [
        {
          "name" : "ポテト野菜サラダ",
          "price" : "121",
          "attr" : "b",
          "img" : "https:\/\/west2-univ.jp\/menu_img\/png_sp\/814418.png"
        },
        {
          "name" : "南瓜コロッケ",
          "attr" : "b",
          "price" : "121",
          "img" : "https:\/\/west2-univ.jp\/menu_img\/png_sp\/814409.png"
        },
        {
          "attr" : "b",
          "price" : "99",
          "img" : "https:\/\/west2-univ.jp\/menu_img\/png_sp\/814447.png",
          "name" : "オクラ巣ごもり玉子"
        },
        {
          "img" : "https:\/\/west2-univ.jp\/menu_img\/png_sp\/814554.png",
          "price" : "99",
          "attr" : "b",
          "name" : "茄子のピリ辛胡麻風味"
        },
        {
          "attr" : "b",
          "img" : "https:\/\/west2-univ.jp\/menu_img\/png_sp\/814539.png",
          "name" : "竹の子土佐煮",
          "price" : "99"
        },
        {
          "price" : "99",
          "attr" : "b",
          "img" : "https:\/\/west2-univ.jp\/menu_img\/png_sp\/814477.png",
          "name" : "春雨しそサラダ"
        },
        {
          "attr" : "b",
          "price" : "99",
          "img" : "https:\/\/west2-univ.jp\/menu_img\/png_sp\/814578.png",
          "name" : "ほうれん草ごまナムル"
        },
        {
          "attr" : "b",
          "img" : "https:\/\/west2-univ.jp\/menu_img\/png_sp\/814434.png",
          "price" : "77",
          "name" : "ほうれん草"
        },
        {
          "name" : "だし巻き",
          "img" : "https:\/\/west2-univ.jp\/menu_img\/png_sp\/814453.png",
          "attr" : "b",
          "price" : "77"
        },
        {
          "price" : "77",
          "attr" : "b",
          "img" : "https:\/\/west2-univ.jp\/menu_img\/png_sp\/814552.png",
          "name" : "きんぴらごぼう"
        },
        {
          "attr" : "b",
          "name" : "スライスオクラ",
          "img" : "https:\/\/west2-univ.jp\/menu_img\/png_sp\/814454.png",
          "price" : "77"
        },
        {
          "img" : "https:\/\/west2-univ.jp\/menu_img\/png_sp\/814455.png",
          "attr" : "b",
          "price" : "55",
          "name" : "冷奴"
        },
        {
          "price" : "55",
          "img" : "https:\/\/west2-univ.jp\/menu_img\/png_sp\/814460.png",
          "name" : "ミニサラダ",
          "attr" : "b"
        },
        {
          "name" : "豚汁",
          "attr" : "b",
          "price" : "121",
          "img" : "https:\/\/west2-univ.jp\/menu_img\/png_sp\/814667.png"
        },
        {
          "img" : "https:\/\/west2-univ.jp\/menu_img\/png_sp\/814666.png",
          "attr" : "b",
          "price" : "44",
          "name" : "味噌汁"
        }
      ],
      "name" : "Kyoyu"
    },
    {
      "foods" : [
        {
          "attr" : "c",
          "price" : "396",
          "name" : "パイタンうどん",
          "img" : "https:\/\/west2-univ.jp\/menu_img\/png_sp\/819362.png"
        },
        {
          "attr" : "c",
          "img" : "https:\/\/west2-univ.jp\/menu_img\/png_sp\/819316.png",
          "name" : "温玉ぶっかけうどん",
          "price" : "352"
        },
        {
          "price" : "352",
          "name" : "温玉ぶっかけそば",
          "img" : "https:\/\/west2-univ.jp\/menu_img\/png_sp\/819317.png",
          "attr" : "c"
        },
        {
          "price" : "352",
          "name" : "きつねうどん",
          "img" : "https:\/\/west2-univ.jp\/menu_img\/png_sp\/819393.png",
          "attr" : "c"
        },
        {
          "price" : "352",
          "img" : "https:\/\/west2-univ.jp\/menu_img\/png_sp\/819394.png",
          "attr" : "c",
          "name" : "きつねそば"
        },
        {
          "attr" : "c",
          "name" : "かけうどん",
          "img" : "https:\/\/west2-univ.jp\/menu_img\/png_sp\/819328.png",
          "price" : "264"
        },
        {
          "img" : "https:\/\/west2-univ.jp\/menu_img\/png_sp\/819329.png",
          "price" : "264",
          "attr" : "c",
          "name" : "かけそば"
        },
        {
          "img" : "https:\/\/west2-univ.jp\/menu_img\/png_sp\/819445.png",
          "attr" : "c",
          "name" : "醤油豚骨ラーメン",
          "price" : "462"
        }
      ],
      "name" : "Kyoyu"
    },
    {
      "name" : "Kyoyu",
      "foods" : [
        {
          "price" : "中495",
          "attr" : "d",
          "img" : "https:\/\/west2-univ.jp\/menu_img\/png_sp\/819232.png",
          "name" : "サーモンビビンバ丼"
        },
        {
          "name" : "サーモンビビンバ丼",
          "price" : "小440",
          "img" : "https:\/\/west2-univ.jp\/menu_img\/png_sp\/819232.png",
          "attr" : "d"
        },
        {
          "name" : "サーモンビビンバ丼",
          "price" : "大550",
          "img" : "https:\/\/west2-univ.jp\/menu_img\/png_sp\/819232.png",
          "attr" : "d"
        },
        {
          "price" : "中440",
          "img" : "https:\/\/west2-univ.jp\/menu_img\/png_sp\/819951.png",
          "name" : "そぼろ親子丼",
          "attr" : "d"
        },
        {
          "attr" : "d",
          "img" : "https:\/\/west2-univ.jp\/menu_img\/png_sp\/819951.png",
          "name" : "そぼろ親子丼",
          "price" : "小385"
        },
        {
          "attr" : "d",
          "name" : "そぼろ親子丼",
          "img" : "https:\/\/west2-univ.jp\/menu_img\/png_sp\/819951.png",
          "price" : "大495"
        },
        {
          "img" : "https:\/\/west2-univ.jp\/menu_img\/png_sp\/819223.png",
          "attr" : "d",
          "name" : "唐揚げ茶漬け丼",
          "price" : "中440"
        },
        {
          "price" : "小385",
          "attr" : "d",
          "img" : "https:\/\/west2-univ.jp\/menu_img\/png_sp\/819223.png",
          "name" : "唐揚げ茶漬け丼"
        },
        {
          "attr" : "d",
          "price" : "大495",
          "name" : "唐揚げ茶漬け丼",
          "img" : "https:\/\/west2-univ.jp\/menu_img\/png_sp\/819223.png"
        },
        {
          "name" : "唐揚げカレー",
          "price" : "中440",
          "img" : "https:\/\/west2-univ.jp\/menu_img\/png_sp\/819256.png",
          "attr" : "d"
        },
        {
          "attr" : "d",
          "img" : "https:\/\/west2-univ.jp\/menu_img\/png_sp\/819256.png",
          "price" : "小385",
          "name" : "唐揚げカレー"
        },
        {
          "attr" : "d",
          "name" : "唐揚げカレー",
          "price" : "大495",
          "img" : "https:\/\/west2-univ.jp\/menu_img\/png_sp\/819256.png"
        },
        {
          "price" : "中319",
          "name" : "カレーライス",
          "img" : "https:\/\/west2-univ.jp\/menu_img\/png_sp\/819272.png",
          "attr" : "d"
        },
        {
          "name" : "カレーライス",
          "attr" : "d",
          "price" : "小264",
          "img" : "https:\/\/west2-univ.jp\/menu_img\/png_sp\/819272.png"
        },
        {
          "img" : "https:\/\/west2-univ.jp\/menu_img\/png_sp\/819272.png",
          "price" : "大374",
          "name" : "カレーライス",
          "attr" : "d"
        },
        {
          "img" : "https:\/\/west2-univ.jp\/menu_img\/png_sp\/814702.png",
          "name" : "ライス",
          "attr" : "d",
          "price" : "中126"
        },
        {
          "img" : "https:\/\/west2-univ.jp\/menu_img\/png_sp\/814702.png",
          "name" : "ライス",
          "attr" : "d",
          "price" : "小105"
        },
        {
          "img" : "https:\/\/west2-univ.jp\/menu_img\/png_sp\/814702.png",
          "price" : "大147",
          "attr" : "d",
          "name" : "ライス"
        }
      ]
    },
    {
      "name" : "Kyoyu",
      "foods" : [
        {
          "price" : "176",
          "name" : "ミルクティーショート",
          "attr" : "e",
          "img" : "https:\/\/west2-univ.jp\/menu_img\/png_sp\/814841.png"
        },
        {
          "name" : "フルーツヨーグルト",
          "price" : "132",
          "attr" : "e",
          "img" : "https:\/\/west2-univ.jp\/menu_img\/png_sp\/814808.png"
        },
        {
          "name" : "バナナクレープ",
          "img" : "https:\/\/west2-univ.jp\/menu_img\/png_sp\/814890.png",
          "price" : "88",
          "attr" : "e"
        },
        {
          "price" : "110",
          "img" : "https:\/\/west2-univ.jp\/menu_img\/png_sp\/814817.png",
          "attr" : "e",
          "name" : "大学芋"
        },
        {
          "attr" : "e",
          "price" : "98",
          "name" : "牛乳",
          "img" : "https:\/\/west2-univ.jp\/menu_img\/png_sp\/814816.png"
        }
      ]
    },
    {
      "name" : "Kyoyu",
      "foods" : [

      ]
    },
    {
      "name" : "Kyoyu",
      "foods" : [

      ]
    }
  ],
  "time" : "2024\/05\/14 08:24"
}